eyeflask/__init__.py
eyeflask/cli.py
eyeflask/extras/eyeflask-sample.cfg
eyeflask/extras/eyeflask.service
eyeflask/extras/nginx.conf
eyeflask/extras/upload_scans.path
eyeflask/extras/upload_scans.service
eyeflask/extras/upload_scans.timer
eyeflask/server/__init__.py
eyeflask/server/crypto.py
eyeflask/server/views.py
eyeflask/server/templates/get_photo_status.xml
eyeflask/server/templates/mark_last.xml
eyeflask/server/templates/start_session.xml
eyeflask/server/templates/upload_photo.xml
eyeflask-0.1.3.dist-info/DESCRIPTION.rst
eyeflask-0.1.3.dist-info/METADATA
eyeflask-0.1.3.dist-info/RECORD
eyeflask-0.1.3.dist-info/WHEEL
eyeflask-0.1.3.dist-info/entry_points.txt
eyeflask-0.1.3.dist-info/metadata.json
eyeflask-0.1.3.dist-info/top_level.txt
tests/__init__.py
tests/conftest.py
tests/mock_payloads.py
tests/test_eyeflask.py
