Metadata-Version: 2.0
Name: eyeflask
Version: 0.1.3
Summary: Flask-based EyeFi Server
Home-page: https://github.com/n8henrie/eyeflask
Author: Nathan Henrie
Author-email: nate@n8henrie.com
License: MIT
Keywords: eyeflask eyefi flask
Platform: UNKNOWN
Classifier: Natural Language :: English
Classifier: Programming Language :: Python :: 3
Classifier: Programming Language :: Python :: 3.4
Classifier: Programming Language :: Python :: 3.5
Classifier: Programming Language :: Python :: 3.6
Requires-Dist: Flask (==0.12)
Requires-Dist: defusedxml (==0.5.0)
Provides-Extra: dev
Requires-Dist: Sphinx (==1.5.3); extra == 'dev'
Requires-Dist: docutils (==0.13.1); extra == 'dev'
Requires-Dist: flake8 (==3.3.0); extra == 'dev'
Requires-Dist: pypandoc (==1.3.3); extra == 'dev'
Requires-Dist: pytest (==3.0.6); extra == 'dev'
Requires-Dist: recommonmark (==0.4.0); extra == 'dev'
Requires-Dist: sphinx-rtd-theme (==0.2.4); extra == 'dev'
Requires-Dist: tox (==2.6.0); extra == 'dev'
Requires-Dist: twine (==1.8.1); extra == 'dev'
